{
  "trigger": "schedule",
  "date": "2026-06-07",
  "publish_date": "2026-06-07",
  "target_date": "2026-06-05",
  "actual_date": null,
  "fallback_days": 4,
  "fallback_used": false,
  "fallback_from": null,
  "mock": false,
  "categories": [
    "cs.AI",
    "cs.CL",
    "cs.LG",
    "cs.CV",
    "cs.MA",
    "cs.IR",
    "cs.RO",
    "cs.SD",
    "cs.MM",
    "cs.HC",
    "cs.SE",
    "cs.DC",
    "stat.ML",
    "eess.AS"
  ],
  "category_counts": {
    "cs.AI": 0,
    "cs.CL": 0,
    "cs.LG": 0,
    "cs.CV": 0,
    "cs.MA": 0,
    "cs.IR": 0,
    "cs.RO": 0,
    "cs.SD": 0,
    "cs.MM": 0,
    "cs.HC": 0,
    "cs.SE": 0,
    "cs.DC": 0,
    "stat.ML": 0,
    "eess.AS": 0
  },
  "total_candidates": 0,
  "deduped_papers": 0,
  "fetch_mode": null,
  "page_count": 0,
  "request_count": 0,
  "page_stats": {},
  "partial_fetch_errors": {},
  "featured": 0,
  "mentions": 0,
  "slugs": {},
  "errors": {
    "cs.AI": "HTTP 429 Too Many Requests",
    "cs.CL": "HTTP 429 Too Many Requests",
    "cs.LG": "HTTP 429 Too Many Requests",
    "cs.CV": "HTTP 429 Too Many Requests",
    "cs.MA": "HTTP 429 Too Many Requests",
    "cs.IR": "HTTP 429 Too Many Requests",
    "cs.RO": "HTTP 429 Too Many Requests",
    "cs.SD": "HTTP 429 Too Many Requests",
    "cs.MM": "HTTP 429 Too Many Requests",
    "cs.HC": "HTTP 429 Too Many Requests",
    "cs.SE": "HTTP 429 Too Many Requests",
    "cs.DC": "HTTP 429 Too Many Requests",
    "stat.ML": "HTTP 429 Too Many Requests",
    "eess.AS": "HTTP 429 Too Many Requests",
    "pipeline": "All arXiv categories failed for 2026-06-05; not using date fallback because this is a fetch failure, not an empty arXiv publication day. Errors: cs.AI: HTTP 429 Too Many Requests; cs.CL: HTTP 429 Too Many Requests; cs.LG: HTTP 429 Too Many Requests; cs.CV: HTTP 429 Too Many Requests; cs.MA: HTTP 429 Too Many Requests; cs.IR: HTTP 429 Too Many Requests; cs.RO: HTTP 429 Too Many Requests; cs.SD: HTTP 429 Too Many Requests; cs.MM: HTTP 429 Too Many Requests; cs.HC: HTTP 429 Too Many Requests; cs.SE: HTTP 429 Too Many Requests; cs.DC: HTTP 429 Too Many Requests; stat.ML: HTTP 429 Too Many Requests; eess.AS: HTTP 429 Too Many Requests"
  },
  "warnings": [],
  "generated_files": [],
  "qa_passed": false,
  "qa_warnings": [],
  "status": "failed",
  "attempts": [
    {
      "date": "2026-06-05",
      "category_counts": {
        "cs.AI": 0,
        "cs.CL": 0,
        "cs.LG": 0,
        "cs.CV": 0,
        "cs.MA": 0,
        "cs.IR": 0,
        "cs.RO": 0,
        "cs.SD": 0,
        "cs.MM": 0,
        "cs.HC": 0,
        "cs.SE": 0,
        "cs.DC": 0,
        "stat.ML": 0,
        "eess.AS": 0
      },
      "errors": {
        "cs.AI": "HTTP 429 Too Many Requests",
        "cs.CL": "HTTP 429 Too Many Requests",
        "cs.LG": "HTTP 429 Too Many Requests",
        "cs.CV": "HTTP 429 Too Many Requests",
        "cs.MA": "HTTP 429 Too Many Requests",
        "cs.IR": "HTTP 429 Too Many Requests",
        "cs.RO": "HTTP 429 Too Many Requests",
        "cs.SD": "HTTP 429 Too Many Requests",
        "cs.MM": "HTTP 429 Too Many Requests",
        "cs.HC": "HTTP 429 Too Many Requests",
        "cs.SE": "HTTP 429 Too Many Requests",
        "cs.DC": "HTTP 429 Too Many Requests",
        "stat.ML": "HTTP 429 Too Many Requests",
        "eess.AS": "HTTP 429 Too Many Requests"
      },
      "total_candidates": 0,
      "deduped_papers": 0,
      "fetch_mode": null,
      "page_count": 0,
      "request_count": 0,
      "page_stats": {},
      "partial_fetch_errors": {},
      "error": null
    }
  ],
  "report_path": "data/reports/runs/2026-06-07.json"
}